crudini.py
crudini-0.9.6.dist-info/licenses/COPYING
crudini-0.9.6.dist-info/METADATA
crudini-0.9.6.dist-info/WHEEL
crudini-0.9.6.dist-info/entry_points.txt
crudini-0.9.6.dist-info/top_level.txt
crudini-0.9.6.dist-info/RECORD
