Metadata-Version: 2.4
Name: crudini
Version: 0.9.6
Summary: A utility for manipulating ini files
Home-page: http://github.com/pixelb/crudini
Author: Pádraig Brady
Author-email: P@draigBrady.com
License: GPLv2
Keywords: ini,config,edit
Classifier: Development Status :: 5 - Production/Stable
Classifier: Topic :: Utilities
Classifier: Topic :: System :: Systems Administration
Classifier: License :: OSI Approved :: GNU General Public License v2 (GPLv2)
Classifier: Programming Language :: Python :: 2
Classifier: Programming Language :: Python :: 3
License-File: COPYING
Requires-Dist: iniparse>=0.5
Dynamic: license-file
